{
  "_type": "policyAnalysis",
  "title": "The Premium Spike: Why 108% Growth is the Breaking Point",
  "slug": {
    "current": "the-premium-spike-breaking-point"
  },
  "publishedAt": "2025-12-14T08:00:00Z",
  "pillar": "Economics",
  "status": "Active",
  "impactLevel": "Critical",
  "summary": "Commercial insurance premiums in Vermont have more than doubled in six years, severing the link between local wages and healthcare costs. This hyper-inflation marks the end of the 'Commercial Cross-Subsidy' as a viable financial strategy for hospitals.",
  "body": [
    {
      "_type": "audio",
      "_key": "aud1",
      "title": "Audio Briefing: The Premium Spike",
      "summary": "A 2-minute overview of the decoupling between wages and insurance costs."
    },
    {
      "_type": "block",
      "_key": "intro1",
      "style": "normal",
      "children": [
        {
          "_type": "span",
          "_key": "span1",
          "text": "The 'Health Economy' runs on a delicate balance: providers raise prices, and payers pass those costs to employers and employees. That cycle has now hit a mathematical wall in Vermont. The Act 167 report data confirms that the price elasticity of the commercial market has snapped.",
          "marks": []
        }
      ],
      "markDefs": []
    },
    {
      "_type": "video",
      "_key": "vid1",
      "url": "https://www.youtube.com/watch?v=LObBnn4Li9Y",
      "caption": "Video: WCAX News report on skyrocketing premiums in Vermont"
    },
    {
      "_type": "block",
      "_key": "h2_1",
      "style": "h2",
      "children": [
        {
          "_type": "span",
          "_key": "sh2_1",
          "text": "1. The 108% Spike",
          "marks": []
        }
      ],
      "markDefs": []
    },
    {
      "_type": "block",
      "_key": "p1",
      "style": "normal",
      "children": [
        {
          "_type": "span",
          "_key": "sp1",
          "text": "The headline metric is staggering. The average monthly premium for a silver exchange plan has risen to $985 in 2024. This represents a ",
          "marks": []
        },
        {
          "_type": "span",
          "_key": "sp1_b",
          "text": "108% increase",
          "marks": ["strong", "highlight-economics"]
        },
        {
          "_type": "span",
          "_key": "sp1_c",
          "text": " since 2018. During that same period, median household income in Vermont grew by only 22%.",
          "marks": []
        }
      ],
      "markDefs": []
    },
    {
      "_type": "code",
      "_key": "table1",
      "language": "json",
      "code": "[{\"Metric\": \"Silver Plan Premium\", \"Growth (6-Year)\": \"+108%\"}, {\"Metric\": \"Hospital Charges\", \"Growth (6-Year)\": \"+38%\"}, {\"Metric\": \"Median Wages\", \"Growth (6-Year)\": \"+22%\"}]"
    },
    {
      "_type": "block",
      "_key": "p2",
      "style": "normal",
      "children": [
        {
          "_type": "span",
          "_key": "sp2",
          "text": "When the cost of the product (insurance) grows 5x faster than the customer's ability to pay (wages), the market is technically broken.",
          "marks": []
        }
      ],
      "markDefs": []
    },
    {
      "_type": "block",
      "_key": "h2_2",
      "style": "h2",
      "children": [
        {
          "_type": "span",
          "_key": "sh2_2",
          "text": "2. The Deductible Cliff",
          "marks": []
        }
      ],
      "markDefs": []
    },
    {
      "_type": "block",
      "_key": "p3",
      "style": "normal",
      "children": [
        {
          "_type": "span",
          "_key": "sp3",
          "text": "It is not just the premiums. The 'protection' value of the insurance is eroding simultaneously. The report highlights that out-of-pocket (OOP) maximums have increased by >100% in the past 5 years.",
          "marks": []
        }
      ],
      "markDefs": []
    },
    {
      "_type": "block",
      "_key": "q1",
      "style": "blockquote",
      "children": [
        {
          "_type": "span",
          "_key": "sq1",
          "text": "“Vermonters cannot afford annual double digit increases in insurance premium costs.”",
          "marks": ["highlight-policy"]
        }
      ],
      "markDefs": []
    },
    {
      "_type": "image",
      "_key": "img1",
      "caption": "Figure 1: The widening gap between Premium Costs and Household Income",
      "alt": "Chart showing the divergence of healthcare costs vs wages"
    },
    {
      "_type": "block",
      "_key": "h2_3",
      "style": "h2",
      "children": [
        {
          "_type": "span",
          "_key": "sh2_3",
          "text": "3. Strategic Implications",
          "marks": []
        }
      ],
      "markDefs": []
    },
    {
      "_type": "block",
      "_key": "h3_1",
      "style": "h3",
      "children": [
        {
          "_type": "span",
          "_key": "sh3_1",
          "text": "ECONOMICS: The Revenue Ceiling",
          "marks": ["highlight-economics"]
        }
      ],
      "markDefs": []
    },
    {
      "_type": "block",
      "_key": "p4",
      "style": "normal",
      "children": [
        {
          "_type": "span",
          "_key": "sp4",
          "text": "The data suggests that hospitals can no longer rely on 'Commercial Rate Lifts' to balance their books. With premiums already at $985/month, further increases will likely drive small businesses to drop coverage entirely. The 'Commercial Cross-Subsidy' lever is stuck.",
          "marks": []
        }
      ],
      "markDefs": []
    },
    {
      "_type": "block",
      "_key": "h3_2",
      "style": "h3",
      "children": [
        {
          "_type": "span",
          "_key": "sh3_2",
          "text": "POLICY: The Binary Choice",
          "marks": ["highlight-policy"]
        }
      ],
      "markDefs": []
    },
    {
      "_type": "block",
      "_key": "p5",
      "style": "normal",
      "children": [
        {
          "_type": "span",
          "_key": "sp5",
          "text": "Vermont regulators are facing a binary choice. The report explicitly notes that 'Higher taxation is unlikely to be a viable solution'. If the state cannot tax its way out, and employers cannot pay their way out, the only remaining policy lever is Service Reduction (closing beds/lines) or Price Controls (Reference-Based Pricing).",
          "marks": []
        }
      ],
      "markDefs": []
    },
    {
      "_type": "block",
      "_key": "h2_4",
      "style": "h2",
      "children": [
        {
          "_type": "span",
          "_key": "sh2_4",
          "text": "HTR Outlook",
          "marks": []
        }
      ],
      "markDefs": []
    },
    {
      "_type": "block",
      "_key": "p6",
      "style": "normal",
      "children": [
        {
          "_type": "span",
          "_key": "sp6",
          "text": "The 'Premium Spike' is the lead indicator for the 'Volume Collapse.' As affordability vanishes, patients defer care. We expect to see a short-term drop in elective utilization followed by a long-term spike in high-acuity emergency cases as untreated conditions worsen.",
          "marks": []
        }
      ],
      "markDefs": []
    }
  ]
}
